sk_variable_handler/__init__.py
sk_variable_handler/variable_handler.py
sk_variable_handler-1.0.102.dist-info/LICENSE.txt
sk_variable_handler-1.0.102.dist-info/METADATA
sk_variable_handler-1.0.102.dist-info/WHEEL
sk_variable_handler-1.0.102.dist-info/top_level.txt
sk_variable_handler-1.0.102.dist-info/RECORD
