Metadata-Version: 2.1
Name: sk-variable-handler
Version: 1.0.102
Summary: A simple Variable Handling  program
Author: gkibria
Author-email: gkibria121@gmail.com
Keywords: python,report generator
Classifier: Programming Language :: Python :: 3
Classifier: License :: OSI Approved :: MIT License
Classifier: Operating System :: OS Independent
Requires-Python: >=3.6
License-File: LICENSE.txt
Requires-Dist: regex
